LICENSE
MANIFEST.in
README.md
requirements.txt
setup.py
test/test_build.py
tomoe/__init__.py
tomoe/asmhentai.py
tomoe/bulk_download.py
tomoe/cli.py
tomoe/hentai2read.py
tomoe/hentaifox.py
tomoe/nhentai.py
tomoe/pdf.py
tomoe/pururin.py
tomoe/simplyh.py
tomoe/threehentai.py
tomoe.egg-info/PKG-INFO
tomoe.egg-info/SOURCES.txt
tomoe.egg-info/dependency_links.txt
tomoe.egg-info/entry_points.txt
tomoe.egg-info/requires.txt
tomoe.egg-info/top_level.txt
tomoe/utils/const.py
tomoe/utils/misc.py
tomoe/utils/request.py