Metadata-Version: 2.1
Name: tomoe
Version: 3.0.15
Summary: A doujinshi downloader with ease
Home-page: https://github.com/sinkaroid/tomoe
Author: sinkaroid
Author-email: anakmancasan@gmail.com
License: MIT
Project-URL: Discord, https://discord.gg/8wj4vM5hHM
Project-URL: Funding, https://paypal.me/sinkaroid
Project-URL: Issue tracker, https://github.com/sinkaroid/tomoe/issues/new/choose
Project-URL: Documentation, https://github.com/sinkaroid/tomoe/wiki
Classifier: Framework :: AsyncIO
Classifier: Development Status :: 3 - Alpha
Classifier: Intended Audience :: Customer Service
Classifier: License :: OSI Approved :: MIT License
Classifier: Natural Language :: English
Classifier: Operating System :: OS Independent
Classifier: Environment :: Console
Classifier: Programming Language :: Python :: 3.7
Classifier: Programming Language :: Python :: 3.8
Classifier: Programming Language :: Python :: 3.9
Classifier: Programming Language :: Python :: 3.10
Classifier: Topic :: Artistic Software
Classifier: Topic :: Games/Entertainment
Classifier: Topic :: Internet :: WWW/HTTP :: Dynamic Content
Classifier: Topic :: Scientific/Engineering :: Image Processing
License-File: LICENSE
